ab_core/user/__init__.py
ab_core/user/model.py
ab_core/user/service.py
ab_user-0.1.9.dist-info/METADATA
ab_user-0.1.9.dist-info/WHEEL
ab_user-0.1.9.dist-info/licenses/LICENSE
ab_user-0.1.9.dist-info/RECORD
