Metadata-Version: 2.4
Name: ab-user
Version: 0.1.9
Author-email: Matthew Coulter <53892067+mattcoulter7@users.noreply.github.com>
License-File: LICENSE
Requires-Python: <4,>=3.12
Requires-Dist: ab-database<0.3.0,>=0.2.1
Requires-Dist: ab-dependency<0.3.0,>=0.2.0
